csvql.py
csvql-0.0.5.dist-info/LICENSE
csvql-0.0.5.dist-info/METADATA
csvql-0.0.5.dist-info/WHEEL
csvql-0.0.5.dist-info/entry_points.txt
csvql-0.0.5.dist-info/top_level.txt
csvql-0.0.5.dist-info/RECORD
