Metadata-Version: 2.1
Name: csvql
Version: 0.0.5
Summary: csvql command line tool
Home-page: https://github.com/Ragnarok540/csvql
Author: Edgar Nova
Author-email: ragnarok540@gmail.com
License: UNKNOWN
Keywords: csv,sql,sqlite,csvql,query
Platform: UNKNOWN
Classifier: Programming Language :: Python :: 3
Classifier: License :: OSI Approved :: MIT License
Classifier: Operating System :: OS Independent
